tiktok_reup/__init__.py
tiktok_reup/cli.py
tiktok_reup/api/__init__.py
tiktok_reup/api/tiktok_api.py
tiktok_reup/config/__init__.py
tiktok_reup/config/settings.py
tiktok_reup/core/__init__.py
tiktok_reup/core/downloader.py
tiktok_reup/selenium_handler/__init__.py
tiktok_reup/selenium_handler/browser.py
tiktok_reup/upload/__init__.py
tiktok_reup/upload/uploader.py
tiktok_reup/utils/__init__.py
tiktok_reup/utils/helpers.py
tiktok_reup-2.0.0.dist-info/licenses/LICENSE
tiktok_reup-2.0.0.dist-info/METADATA
tiktok_reup-2.0.0.dist-info/WHEEL
tiktok_reup-2.0.0.dist-info/entry_points.txt
tiktok_reup-2.0.0.dist-info/top_level.txt
tiktok_reup-2.0.0.dist-info/RECORD
