Metadata-Version: 2.4
Name: tiktok-reup
Version: 2.0.0
Summary: A modular Python package for downloading and uploading TikTok videos
Home-page: https://github.com/xuancuong2006/tiktok-reup
Author: xuancuong2006
Author-email: xuancuong2006@gmail.com
Maintainer: xuancuong2006
License: MIT
Project-URL: Homepage, https://github.com/xuancuong2006/tiktok-reup
Project-URL: Bug Reports, https://github.com/xuancuong2006/tiktok-reup/issues
Project-URL: Source, https://github.com/xuancuong2006/tiktok-reup
Project-URL: Telegram, https://t.me/xuancuong2006
Keywords: tiktok,video,download,upload,social media,automation,scraping
Classifier: Development Status :: 4 - Beta
Classifier: Intended Audience :: End Users/Desktop
Classifier: Topic :: Internet :: WWW/HTTP :: Dynamic Content
Classifier: Topic :: Multimedia :: Video
Classifier: License :: OSI Approved :: MIT License
Classifier: Operating System :: OS Independent
Classifier: Programming Language :: Python :: 3
Classifier: Programming Language :: Python :: 3.8
Classifier: Programming Language :: Python :: 3.9
Classifier: Programming Language :: Python :: 3.10
Classifier: Programming Language :: Python :: 3.11
Classifier: Programming Language :: Python :: 3.12
Requires-Python: >=3.8
License-File: LICENSE
Requires-Dist: requests>=2.31.0
Requires-Dist: tqdm>=4.65.0
Requires-Dist: colorama>=0.4.6
Requires-Dist: yt-dlp>=2023.7.6
Requires-Dist: selenium>=4.15.0
Requires-Dist: webdriver-manager>=4.0.1
Requires-Dist: urllib3>=1.26.0
Requires-Dist: certifi>=2023.7.22
Dynamic: author-email
Dynamic: home-page
Dynamic: license-file
Dynamic: requires-python
